[
  {
    "id": 88,
    "name": "펫엔조이 애견미용 구래점",
    "fullAddress": "경기 김포시 구래동",
    "province": "경기",
    "city": "김포시",
    "district": "구래동",
    "addr": "경기 김포시 솔터로 22",
    "imgUrl": "https://search.pstatic.net/common/?autoRotate=true&quality=100&type=f640_380&src=https%3A%2F%2Fldb-phinf.pstatic.net%2F20220712_48%2F1657596436579YRRGf_JPEG%2F500pxdownload.com-206618921.jpg",
    "operatingHours": [
      {
        "dayOfWeek": 6,
        "openTime": null,
        "closeTime": null,
        "holiday": false
      },
      {
        "dayOfWeek": 1,
        "openTime": "00:00",
        "closeTime": "00:05",
        "holiday": false
      },
      {
        "dayOfWeek": 2,
        "openTime": null,
        "closeTime": null,
        "holiday": false
      },
      {
        "dayOfWeek": 5,
        "openTime": null,
        "closeTime": null,
        "holiday": false
      },
      {
        "dayOfWeek": 3,
        "openTime": null,
        "closeTime": null,
        "holiday": false
      },
      {
        "dayOfWeek": 4,
        "openTime": null,
        "closeTime": null,
        "holiday": false
      },
      {
        "dayOfWeek": 0,
        "openTime": null,
        "closeTime": null,
        "holiday": false
      }
    ],
    "openNow": false,
    "amenities": [
      "예약",
      "반려동물 동반",
      "주차"
    ]
  },
  {
    "id": 8,
    "name": "댕데이지",
    "fullAddress": "경기 김포시 구래동",
    "province": "경기",
    "city": "김포시",
    "district": "구래동",
    "addr": "경기 김포시 솔터로 22",
    "imgUrl": "https://search.pstatic.net/common/?autoRotate=true&quality=100&type=f640_380&src=https%3A%2F%2Fldb-phinf.pstatic.net%2F20250824_175%2F1756035262883NAwpg_JPEG%2FDF4A1EE6-57BB-4F5D-A987-38CC4F313A6C.jpeg",
    "operatingHours": [
      {
        "dayOfWeek": 6,
        "openTime": "09:00",
        "closeTime": "22:00",
        "holiday": false
      },
      {
        "dayOfWeek": 1,
        "openTime": "10:00",
        "closeTime": "18:00",
        "holiday": false
      },
      {
        "dayOfWeek": 2,
        "openTime": "10:00",
        "closeTime": "18:00",
        "holiday": false
      },
      {
        "dayOfWeek": 5,
        "openTime": "10:00",
        "closeTime": "18:00",
        "holiday": false
      },
      {
        "dayOfWeek": 3,
        "openTime": "10:00",
        "closeTime": "18:00",
        "holiday": false
      },
      {
        "dayOfWeek": 4,
        "openTime": "10:00",
        "closeTime": "18:00",
        "holiday": false
      },
      {
        "dayOfWeek": 0,
        "openTime": "09:00",
        "closeTime": "22:00",
        "holiday": false
      }
    ],
    "openNow": true,
    "amenities": [
      "예약",
      "반려동물 동반",
      "남/녀 화장실 구분",
      "주차"
    ]
  },
  {
    "id": 28,
    "name": "카페몽몽",
    "fullAddress": "경기 김포시 구래동",
    "province": "경기",
    "city": "김포시",
    "district": "구래동",
    "addr": "경기 김포시 김포한강9로75번길 102",
    "imgUrl": "https://search.pstatic.net/common/?autoRotate=true&quality=100&type=f640_380&src=https%3A%2F%2Fldb-phinf.pstatic.net%2F20190320_127%2F15530613685991JjzH_PNG%2FSGQwptsbrFJMnRpl_qLC4SMx.png",
    "operatingHours": [
      {
        "dayOfWeek": 6,
        "openTime": "10:00",
        "closeTime": "22:00",
        "holiday": false
      },
      {
        "dayOfWeek": 1,
        "openTime": "12:00",
        "closeTime": "22:00",
        "holiday": false
      },
      {
        "dayOfWeek": 2,
        "openTime": "12:00",
        "closeTime": "22:00",
        "holiday": false
      },
      {
        "dayOfWeek": 5,
        "openTime": "12:00",
        "closeTime": "22:00",
        "holiday": false
      },
      {
        "dayOfWeek": 3,
        "openTime": "12:00",
        "closeTime": "22:00",
        "holiday": false
      },
      {
        "dayOfWeek": 4,
        "openTime": "12:00",
        "closeTime": "22:00",
        "holiday": false
      },
      {
        "dayOfWeek": 0,
        "openTime": "10:00",
        "closeTime": "22:00",
        "holiday": false
      }
    ],
    "openNow": true,
    "amenities": [
      "주차",
      "무선 인터넷",
      "반려동물 동반",
      "남/녀 화장실 구분",
      "단체 이용 가능",
      "예약"
    ]
  },
  {
    "id": 26,
    "name": "프리티 멍",
    "fullAddress": "경기 김포시 구래동",
    "province": "경기",
    "city": "김포시",
    "district": "구래동",
    "addr": "경기 김포시 김포한강4로420번길 98",
    "imgUrl": "https://search.pstatic.net/common/?autoRotate=true&quality=100&type=f640_380&src=https%3A%2F%2Fldb-phinf.pstatic.net%2F20221104_57%2F1667536880637pe8HN_JPEG%2F7578ADA4-534C-4532-A53A-EF6C8063B61F.jpeg",
    "operatingHours": [
      {
        "dayOfWeek": 0,
        "openTime": "09:00",
        "closeTime": "19:00",
        "holiday": false
      },
      {
        "dayOfWeek": 1,
        "openTime": "09:00",
        "closeTime": "19:00",
        "holiday": false
      },
      {
        "dayOfWeek": 2,
        "openTime": "09:00",
        "closeTime": "19:00",
        "holiday": false
      },
      {
        "dayOfWeek": 3,
        "openTime": "09:00",
        "closeTime": "19:00",
        "holiday": false
      },
      {
        "dayOfWeek": 4,
        "openTime": "09:00",
        "closeTime": "19:00",
        "holiday": false
      },
      {
        "dayOfWeek": 5,
        "openTime": "09:00",
        "closeTime": "19:00",
        "holiday": false
      },
      {
        "dayOfWeek": 6,
        "openTime": "09:00",
        "closeTime": "19:00",
        "holiday": false
      }
    ],
    "openNow": true,
    "amenities": [
      "예약",
      "반려동물 동반",
      "남/녀 화장실 구분",
      "무선 인터넷",
      "주차"
    ]
  },
  {
    "id": 30,
    "name": "써니펫살롱",
    "fullAddress": "경기 김포시 구래동",
    "province": "경기",
    "city": "김포시",
    "district": "구래동",
    "addr": "경기 김포시 김포한강8로 396",
    "imgUrl": "https://search.pstatic.net/common/?autoRotate=true&quality=100&type=f640_380&src=https%3A%2F%2Fldb-phinf.pstatic.net%2F20210322_257%2F1616366398046vPP80_JPEG%2FM2InHxgxLYqdNJLDVC-esJmP.jpeg.jpg",
    "operatingHours": [
      {
        "dayOfWeek": 6,
        "openTime": "10:00",
        "closeTime": "19:00",
        "holiday": false
      },
      {
        "dayOfWeek": 1,
        "openTime": "10:00",
        "closeTime": "19:00",
        "holiday": false
      },
      {
        "dayOfWeek": 2,
        "openTime": "10:00",
        "closeTime": "19:00",
        "holiday": false
      },
      {
        "dayOfWeek": 5,
        "openTime": "10:00",
        "closeTime": "19:00",
        "holiday": false
      },
      {
        "dayOfWeek": 3,
        "openTime": "10:00",
        "closeTime": "19:00",
        "holiday": false
      },
      {
        "dayOfWeek": 4,
        "openTime": "10:00",
        "closeTime": "19:00",
        "holiday": false
      },
      {
        "dayOfWeek": 0,
        "openTime": "10:00",
        "closeTime": "19:00",
        "holiday": false
      }
    ],
    "openNow": true,
    "amenities": [
      "무선 인터넷",
      "남/녀 화장실 구분",
      "반려동물 동반",
      "주차"
    ]
  },
  {
    "id": 31,
    "name": "예쁘댕",
    "fullAddress": "경기 김포시 구래동",
    "province": "경기",
    "city": "김포시",
    "district": "구래동",
    "addr": "경기 김포시 솔터로 22",
    "imgUrl": "https://search.pstatic.net/common/?autoRotate=true&quality=100&type=f640_380&src=https%3A%2F%2Fldb-phinf.pstatic.net%2F20250515_251%2F1747274296519hYGQq_PNG%2F1731841304049.png",
    "operatingHours": [
      {
        "dayOfWeek": 0,
        "openTime": "10:00",
        "closeTime": "19:00",
        "holiday": false
      },
      {
        "dayOfWeek": 1,
        "openTime": "10:00",
        "closeTime": "19:00",
        "holiday": false
      },
      {
        "dayOfWeek": 2,
        "openTime": "10:00",
        "closeTime": "19:00",
        "holiday": false
      },
      {
        "dayOfWeek": 3,
        "openTime": "10:00",
        "closeTime": "19:00",
        "holiday": false
      },
      {
        "dayOfWeek": 4,
        "openTime": "10:00",
        "closeTime": "19:00",
        "holiday": false
      },
      {
        "dayOfWeek": 5,
        "openTime": "10:00",
        "closeTime": "19:00",
        "holiday": false
      },
      {
        "dayOfWeek": 6,
        "openTime": "10:00",
        "closeTime": "19:00",
        "holiday": false
      }
    ],
    "openNow": true,
    "amenities": [
      "무선 인터넷",
      "반려동물 동반",
      "남/녀 화장실 구분",
      "예약",
      "주차"
    ]
  },
  {
    "id": 66,
    "name": "플라이투더뭉 애견유치원&애견호텔&애견미용&돌봄",
    "fullAddress": "경기 김포시 구래동",
    "province": "경기",
    "city": "김포시",
    "district": "구래동",
    "addr": "경기 김포시 김포한강9로75번길 10",
    "imgUrl": "https://search.pstatic.net/common/?autoRotate=true&quality=100&type=f640_380&src=https%3A%2F%2Fldb-phinf.pstatic.net%2F20241017_82%2F1729157046152WOmAk_JPEG%2FKakaoTalk_20241017_175702212_03.jpg",
    "operatingHours": [
      {
        "dayOfWeek": 6,
        "openTime": "08:00",
        "closeTime": "20:00",
        "holiday": false
      },
      {
        "dayOfWeek": 1,
        "openTime": "07:00",
        "closeTime": "19:30",
        "holiday": false
      },
      {
        "dayOfWeek": 2,
        "openTime": "07:00",
        "closeTime": "19:30",
        "holiday": false
      },
      {
        "dayOfWeek": 5,
        "openTime": "07:00",
        "closeTime": "19:30",
        "holiday": false
      },
      {
        "dayOfWeek": 3,
        "openTime": "07:00",
        "closeTime": "19:30",
        "holiday": false
      },
      {
        "dayOfWeek": 4,
        "openTime": "07:00",
        "closeTime": "19:30",
        "holiday": false
      },
      {
        "dayOfWeek": 0,
        "openTime": "08:00",
        "closeTime": "20:00",
        "holiday": false
      }
    ],
    "openNow": true,
    "amenities": [
      "반려동물 동반",
      "예약",
      "주차"
    ]
  },
  {
    "id": 64,
    "name": "꽃개하우스",
    "fullAddress": "경기 김포시 구래동",
    "province": "경기",
    "city": "김포시",
    "district": "구래동",
    "addr": "경기 김포시 솔터로 22",
    "imgUrl": "https://search.pstatic.net/common/?autoRotate=true&quality=100&type=f640_380&src=https%3A%2F%2Fldb-phinf.pstatic.net%2F20230808_278%2F1691504963406MgimC_JPEG%2FScreenshot_20220816-130250_Gallery.jpg",
    "operatingHours": [
      {
        "dayOfWeek": 6,
        "openTime": "10:00",
        "closeTime": "16:00",
        "holiday": false
      },
      {
        "dayOfWeek": 1,
        "openTime": "10:00",
        "closeTime": "18:00",
        "holiday": false
      },
      {
        "dayOfWeek": 2,
        "openTime": "10:00",
        "closeTime": "18:00",
        "holiday": false
      },
      {
        "dayOfWeek": 5,
        "openTime": "10:00",
        "closeTime": "18:00",
        "holiday": false
      },
      {
        "dayOfWeek": 3,
        "openTime": "10:00",
        "closeTime": "18:00",
        "holiday": false
      },
      {
        "dayOfWeek": 4,
        "openTime": "10:00",
        "closeTime": "18:00",
        "holiday": false
      },
      {
        "dayOfWeek": 0,
        "openTime": "10:00",
        "closeTime": "16:00",
        "holiday": false
      }
    ],
    "openNow": true,
    "amenities": [
      "반려동물 동반",
      "예약",
      "남/녀 화장실 구분",
      "주차"
    ]
  },
  {
    "id": 67,
    "name": "개인생뽐나개",
    "fullAddress": "경기 김포시 구래동",
    "province": "경기",
    "city": "김포시",
    "district": "구래동",
    "addr": "경기 김포시 김포한강9로75번길 132",
    "imgUrl": "https://search.pstatic.net/common/?autoRotate=true&quality=100&type=f640_380&src=https%3A%2F%2Fldb-phinf.pstatic.net%2F20250719_149%2F1752860062650gHWUq_JPEG%2F9AB83ADD-A316-4C38-A055-418E962967C0.jpeg",
    "operatingHours": [
      {
        "dayOfWeek": 0,
        "openTime": "12:00",
        "closeTime": "23:00",
        "holiday": false
      },
      {
        "dayOfWeek": 1,
        "openTime": "12:00",
        "closeTime": "23:00",
        "holiday": false
      },
      {
        "dayOfWeek": 2,
        "openTime": "12:00",
        "closeTime": "23:00",
        "holiday": false
      },
      {
        "dayOfWeek": 3,
        "openTime": "12:00",
        "closeTime": "23:00",
        "holiday": false
      },
      {
        "dayOfWeek": 4,
        "openTime": "12:00",
        "closeTime": "23:00",
        "holiday": false
      },
      {
        "dayOfWeek": 5,
        "openTime": "12:00",
        "closeTime": "23:00",
        "holiday": false
      },
      {
        "dayOfWeek": 6,
        "openTime": "12:00",
        "closeTime": "23:00",
        "holiday": false
      }
    ],
    "openNow": true,
    "amenities": [
      "대기공간",
      "반려동물 동반",
      "예약",
      "간편결제",
      "주차"
    ]
  },
  {
    "id": 62,
    "name": "도그",
    "fullAddress": "경기 김포시 구래동",
    "province": "경기",
    "city": "김포시",
    "district": "구래동",
    "addr": "경기 김포시 김포한강4로 471",
    "imgUrl": "https://search.pstatic.net/common/?autoRotate=true&quality=100&type=f640_380&src=https%3A%2F%2Fldb-phinf.pstatic.net%2F20190715_291%2F1563181570315EG9lf_JPEG%2FfJe6o_b0n67_JHILn8sO5Dl0.jpg",
    "operatingHours": [
      {
        "dayOfWeek": 6,
        "openTime": "11:00",
        "closeTime": "19:00",
        "holiday": false
      },
      {
        "dayOfWeek": 1,
        "openTime": "11:00",
        "closeTime": "19:00",
        "holiday": false
      },
      {
        "dayOfWeek": 2,
        "openTime": "11:00",
        "closeTime": "19:00",
        "holiday": false
      },
      {
        "dayOfWeek": 5,
        "openTime": null,
        "closeTime": null,
        "holiday": false
      },
      {
        "dayOfWeek": 3,
        "openTime": "11:00",
        "closeTime": "19:00",
        "holiday": false
      },
      {
        "dayOfWeek": 4,
        "openTime": null,
        "closeTime": null,
        "holiday": false
      },
      {
        "dayOfWeek": 0,
        "openTime": "11:00",
        "closeTime": "19:00",
        "holiday": false
      }
    ],
    "openNow": true,
    "amenities": [
      "반려동물 동반",
      "남/녀 화장실 구분",
      "무선 인터넷",
      "주차"
    ]
  }
]